task_attach/__init__.py
task_attach/add.py
task_attach/config.py
task_attach/menu.py
task_attach/new.py
task_attach/open.py
task_attach/select_task.py
task_attach/utils.py
task_attach-0.1.0.data/scripts/mutt2task
task_attach-0.1.0.data/scripts/open-via-mutt
task_attach-0.1.0.data/scripts/task-attach-add
task_attach-0.1.0.data/scripts/task-attach-new
task_attach-0.1.0.data/scripts/task-attach-open
task_attach-0.1.0.dist-info/LICENSE
task_attach-0.1.0.dist-info/METADATA
task_attach-0.1.0.dist-info/WHEEL
task_attach-0.1.0.dist-info/top_level.txt
task_attach-0.1.0.dist-info/RECORD
