Metadata-Version: 2.1
Name: task-attach
Version: 0.1.0
Summary: Scripts to manage attachments in taskwarrior
Home-page: UNKNOWN
Author: Albert Kim
Author-email: alkim@alkim.org
License: UNKNOWN
Platform: UNKNOWN
Requires-Dist: pyyaml
Requires-Dist: tasklib
